README.md
setup.py
test/test_sched.py
tinysched/__init__.py
tinysched/scheduler.py
tinysched.egg-info/PKG-INFO
tinysched.egg-info/SOURCES.txt
tinysched.egg-info/dependency_links.txt
tinysched.egg-info/top_level.txt