Metadata-Version: 1.1
Name: tinysched
Version: 0.1.0
Summary: Easily execute code repeatedly in background
Home-page: https://github.com/dbjohnson/tinysched
Author: Bryan Johnson
Author-email: d.bryan.johnson@gmail.com
License: UNKNOWN
Download-URL: https://github.com/dbjohnson/tinysched/tarball/0.1.0
Platform: UNKNOWN
